beevol/__init__.py
beevol/cli.py
beevol/config.yml
beevol/hive.py
beevol/swarm.py
beevol-0.1.0a0.dist-info/METADATA
beevol-0.1.0a0.dist-info/WHEEL
beevol-0.1.0a0.dist-info/top_level.txt
beevol-0.1.0a0.dist-info/RECORD
