Metadata-Version: 2.4
Name: beevol
Version: 0.1.0a0
Summary: Bifurcated Extremal Entropy
Author-email: Noah Woltman <npwoltman@gmail.com>
License: MIT
Classifier: Development Status :: 3 - Alpha
Classifier: Intended Audience :: Science/Research
Classifier: Programming Language :: Python :: 3
Requires-Python: >=3.8
Requires-Dist: numpy
Requires-Dist: pandas
Requires-Dist: matplotlib
Requires-Dist: scipy
